{"file":"clubjson.png","frames":{
"poker_11_club_3":{"x":58,"y":0,"w":56,"h":67,"offX":0,"offY":1,"sourceW":56,"sourceH":68},
"poker_12":{"x":232,"y":70,"w":14,"h":23,"offX":3,"offY":0,"sourceW":20,"sourceH":23},
"poker_12_club_0":{"x":0,"y":135,"w":52,"h":67,"offX":2,"offY":1,"sourceW":56,"sourceH":68},
"poker_12_club_1":{"x":114,"y":134,"w":52,"h":68,"offX":2,"offY":0,"sourceW":56,"sourceH":68},
"poker_12_club_2":{"x":54,"y":137,"w":52,"h":67,"offX":2,"offY":1,"sourceW":56,"sourceH":68},
"poker_12_club_3":{"x":168,"y":134,"w":52,"h":67,"offX":2,"offY":1,"sourceW":56,"sourceH":68},
"poker_13":{"x":238,"y":167,"w":15,"h":20,"offX":3,"offY":3,"sourceW":20,"sourceH":23},
"poker_13_club_0":{"x":116,"y":0,"w":56,"h":66,"offX":0,"offY":2,"sourceW":56,"sourceH":68},
"poker_13_club_1":{"x":116,"y":68,"w":56,"h":64,"offX":0,"offY":4,"sourceW":56,"sourceH":68},
"poker_13_club_2":{"x":0,"y":69,"w":56,"h":64,"offX":0,"offY":4,"sourceW":56,"sourceH":68},
"poker_13_club_3":{"x":174,"y":68,"w":56,"h":64,"offX":0,"offY":4,"sourceW":56,"sourceH":68},
"poker_14":{"x":232,"y":0,"w":20,"h":21,"offX":0,"offY":2,"sourceW":20,"sourceH":23},
"poker_club_0":{"x":168,"y":203,"w":49,"h":57,"offX":1,"offY":0,"sourceW":50,"sourceH":57},
"poker_club_1":{"x":108,"y":204,"w":49,"h":51,"offX":1,"offY":3,"sourceW":50,"sourceH":57},
"poker_club_2":{"x":0,"y":204,"w":50,"h":51,"offX":0,"offY":3,"sourceW":50,"sourceH":57},
"poker_club_3":{"x":52,"y":206,"w":43,"h":53,"offX":4,"offY":2,"sourceW":50,"sourceH":57},
"poker_2":{"x":222,"y":191,"w":14,"h":21,"offX":3,"offY":2,"sourceW":20,"sourceH":23},
"poker_3":{"x":222,"y":167,"w":14,"h":22,"offX":3,"offY":1,"sourceW":20,"sourceH":23},
"poker_4":{"x":238,"y":212,"w":14,"h":21,"offX":3,"offY":2,"sourceW":20,"sourceH":23},
"poker_5":{"x":238,"y":143,"w":14,"h":22,"offX":3,"offY":1,"sourceW":20,"sourceH":23},
"poker_6":{"x":222,"y":143,"w":14,"h":22,"offX":3,"offY":1,"sourceW":20,"sourceH":23},
"poker_7":{"x":238,"y":189,"w":14,"h":21,"offX":3,"offY":2,"sourceW":20,"sourceH":23},
"poker_8":{"x":232,"y":119,"w":14,"h":22,"offX":3,"offY":1,"sourceW":20,"sourceH":23},
"poker_9":{"x":232,"y":95,"w":14,"h":22,"offX":3,"offY":1,"sourceW":20,"sourceH":23},
"poker_10":{"x":232,"y":23,"w":19,"h":21,"offX":1,"offY":2,"sourceW":20,"sourceH":23},
"poker_11":{"x":232,"y":46,"w":15,"h":22,"offX":3,"offY":1,"sourceW":20,"sourceH":23},
"poker_11_club_0":{"x":0,"y":0,"w":56,"h":67,"offX":0,"offY":1,"sourceW":56,"sourceH":68},
"poker_11_club_1":{"x":174,"y":0,"w":56,"h":66,"offX":0,"offY":2,"sourceW":56,"sourceH":68},
"poker_11_club_2":{"x":58,"y":69,"w":54,"h":66,"offX":1,"offY":2,"sourceW":56,"sourceH":68}}}